vrp/__init__.py
vrp/draw.py
vrp/vrp.py
VRP-0.0.3.dist-info/LICENSE
VRP-0.0.3.dist-info/METADATA
VRP-0.0.3.dist-info/WHEEL
VRP-0.0.3.dist-info/top_level.txt
VRP-0.0.3.dist-info/RECORD
