Metadata-Version: 2.1
Name: VRP
Version: 0.0.3
Summary: A Python package for plotting Vehicle Routing Problem (VRP) solutions.
Home-page: https://github.com/phguo/PyVRP
Author: Penghui Guo
Author-email: m@guo.ph
License: GPL-3.0
Platform: UNKNOWN
Requires-Dist: matplotlib
